objectDetection/__init__.py
objectDetection/create_data_lists.py
objectDetection/datasets.py
objectDetection/definitions.py
objectDetection/detect.py
objectDetection/eval.py
objectDetection/inferencing.py
objectDetection/jutils.py
objectDetection/model.py
objectDetection/train.py
objectDetection/utils.py
ObjectDetection_aeye-0.0.3.dist-info/METADATA
ObjectDetection_aeye-0.0.3.dist-info/WHEEL
ObjectDetection_aeye-0.0.3.dist-info/top_level.txt
ObjectDetection_aeye-0.0.3.dist-info/RECORD
