Metadata-Version: 2.1
Name: ObjectDetection-aeye
Version: 0.0.3
Summary: Object Detection package for Aeye
Home-page: https://github.com/jjmachan/objectdetection-aye
Author: jjmachan
Author-email: jamesjithin97@gmail.com
License: UNKNOWN
Platform: UNKNOWN
Classifier: Programming Language :: Python :: 3
Classifier: License :: OSI Approved :: MIT License
Classifier: Operating System :: OS Independent
Requires-Python: >=3.6
